port_checker/__init__.py
port_checker/cli.py
port_checker/port_checker.py
port_checker-0.2.0.dist-info/AUTHORS.rst
port_checker-0.2.0.dist-info/LICENSE
port_checker-0.2.0.dist-info/METADATA
port_checker-0.2.0.dist-info/WHEEL
port_checker-0.2.0.dist-info/entry_points.txt
port_checker-0.2.0.dist-info/top_level.txt
port_checker-0.2.0.dist-info/RECORD
